file_server/__init__.py
file_server/cli.py
file_server/server.py
file_server/static/bootstrap/css/bootstrap-theme.css
file_server/static/bootstrap/css/bootstrap-theme.css.map
file_server/static/bootstrap/css/bootstrap-theme.min.css
file_server/static/bootstrap/css/bootstrap-theme.min.css.map
file_server/static/bootstrap/css/bootstrap.css
file_server/static/bootstrap/css/bootstrap.css.map
file_server/static/bootstrap/css/bootstrap.min.css
file_server/static/bootstrap/css/bootstrap.min.css.map
file_server/static/bootstrap/fonts/glyphicons-halflings-regular.eot
file_server/static/bootstrap/fonts/glyphicons-halflings-regular.svg
file_server/static/bootstrap/fonts/glyphicons-halflings-regular.ttf
file_server/static/bootstrap/fonts/glyphicons-halflings-regular.woff
file_server/static/bootstrap/fonts/glyphicons-halflings-regular.woff2
file_server/static/bootstrap/js/bootstrap.js
file_server/static/bootstrap/js/bootstrap.min.js
file_server/static/bootstrap/js/jquery-3.6.1.min.js
file_server/static/bootstrap/js/npm.js
file_server/static/fileinput/css/fileinput-rtl.css
file_server/static/fileinput/css/fileinput-rtl.min.css
file_server/static/fileinput/css/fileinput.css
file_server/static/fileinput/css/fileinput.min.css
file_server/static/fileinput/examples/index-bs3.html
file_server/static/fileinput/examples/index-bs4.html
file_server/static/fileinput/examples/index-bs5.html
file_server/static/fileinput/img/loading-sm.gif
file_server/static/fileinput/img/loading.gif
file_server/static/fileinput/js/fileinput.js
file_server/static/fileinput/js/fileinput.min.js
file_server/static/fileinput/js/locales/LANG.js
file_server/static/fileinput/js/locales/ar.js
file_server/static/fileinput/js/locales/az.js
file_server/static/fileinput/js/locales/bg.js
file_server/static/fileinput/js/locales/ca.js
file_server/static/fileinput/js/locales/cr.js
file_server/static/fileinput/js/locales/cs.js
file_server/static/fileinput/js/locales/da.js
file_server/static/fileinput/js/locales/de.js
file_servers-0.1.0.dist-info/METADATA
file_servers-0.1.0.dist-info/WHEEL
file_servers-0.1.0.dist-info/entry_points.txt
file_servers-0.1.0.dist-info/RECORD
