Metadata-Version: 2.1
Name: file-servers
Version: 0.1.0
Summary: file server
Author-Email: funcdefmain <741132517@qq.com>
License: MIT
Requires-Python: >=3.10
Requires-Dist: flask>=3.1.0
